[
  {
    "slug": "sent:tatoeba-230979",
    "jp": "あの子には興奮させられるぜ。",
    "jp_source": "tatoeba:230979",
    "en": "That girl just drives me wild.",
    "target": "させられる",
    "topic": "top:n4-obrigacao",
    "level": "n4",
    "tokens": [
      {
        "position": 0,
        "surface": "あの",
        "lemma": "あの",
        "reading": "あの",
        "pos_coarse": "連体詞",
        "pos_fine": "*",
        "is_particle": false,
        "gloss_en": "that"
      },
      {
        "position": 1,
        "surface": "子",
        "lemma": "子",
        "reading": "こ",
        "pos_coarse": "名詞",
        "pos_fine": "普通名詞",
        "is_particle": false,
        "gloss_en": "child"
      },
      {
        "position": 2,
        "surface": "に",
        "lemma": "に",
        "reading": "に",
        "pos_coarse": "助詞",
        "pos_fine": "格助詞",
        "is_particle": true,
        "gloss_en": null
      },
      {
        "position": 3,
        "surface": "は",
        "lemma": "は",
        "reading": "わ",
        "pos_coarse": "助詞",
        "pos_fine": "係助詞",
        "is_particle": true,
        "gloss_en": null
      },
      {
        "position": 4,
        "surface": "興奮",
        "lemma": "興奮",
        "reading": "こうふん",
        "pos_coarse": "名詞",
        "pos_fine": "普通名詞",
        "is_particle": false,
        "gloss_en": null
      },
      {
        "position": 5,
        "surface": "さ",
        "lemma": "する",
        "reading": "さ",
        "pos_coarse": "動詞",
        "pos_fine": "非自立可能",
        "is_particle": false,
        "gloss_en": "to print"
      },
      {
        "position": 6,
        "surface": "せ",
        "lemma": "せる",
        "reading": "せ",
        "pos_coarse": "助動詞",
        "pos_fine": "*",
        "is_particle": false,
        "gloss_en": null
      },
      {
        "position": 7,
        "surface": "られる",
        "lemma": "られる",
        "reading": "られる",
        "pos_coarse": "助動詞",
        "pos_fine": "*",
        "is_particle": false,
        "gloss_en": null
      },
      {
        "position": 8,
        "surface": "ぜ",
        "lemma": "ぜ",
        "reading": "ぜ",
        "pos_coarse": "助詞",
        "pos_fine": "終助詞",
        "is_particle": true,
        "gloss_en": null
      },
      {
        "position": 9,
        "surface": "。",
        "lemma": "。",
        "reading": "。",
        "pos_coarse": "補助記号",
        "pos_fine": "句点",
        "is_particle": false,
        "gloss_en": null
      }
    ],
    "particles": [
      {
        "position": 2,
        "particle": "に"
      },
      {
        "position": 3,
        "particle": "は"
      },
      {
        "position": 8,
        "particle": "ぜ"
      }
    ],
    "grammar_candidates": [
      {
        "key": "ga-suru",
        "pattern": "がする",
        "label": "sentir/perceber pelos sentidos (〜がする)"
      },
      {
        "key": "gp-117",
        "pattern": "ないと",
        "label": "\"tenho que\" / \"se não...\" (〜ないと)"
      },
      {
        "key": "gp-135",
        "pattern": "Question-phrase + か",
        "label": "pergunta embutida / partícula か em interrogação (疑問詞 + か)"
      },
      {
        "key": "gp-69",
        "pattern": "とうとう",
        "label": "finalmente / por fim (とうとう)"
      },
      {
        "key": "gp-90",
        "pattern": "各",
        "label": "各 (kaku) — \"cada\""
      },
      {
        "key": "ka-shira",
        "pattern": "かしら",
        "label": "será que...? (かしら, feminino)"
      },
      {
        "key": "nagara",
        "pattern": "～ながら",
        "label": "enquanto faz (〜ながら)"
      },
      {
        "key": "saserareru",
        "pattern": "～させられる",
        "label": "causativo-passivo 〜させられる (ser obrigado a fazer)"
      },
      {
        "key": "te-yaru",
        "pattern": "てやる",
        "label": "fazer algo por/para alguém (〜てやる)"
      },
      {
        "key": "zehi",
        "pattern": "ぜひ",
        "label": "ぜひ (zehi) — \"com certeza / não deixe de\""
      }
    ]
  },
  {
    "slug": "sent:tatoeba-150664",
    "jp": "時はすぐたってしまう。",
    "jp_source": "tatoeba:150664",
    "en": "Time passes by quickly.",
    "target": "てしまう",
    "topic": "top:n4-aspecto",
    "level": "n4",
    "tokens": [
      {
        "position": 0,
        "surface": "時",
        "lemma": "時",
        "reading": "とき",
        "pos_coarse": "名詞",
        "pos_fine": "普通名詞",
        "is_particle": false,
        "gloss_en": "hour"
      },
      {
        "position": 1,
        "surface": "は",
        "lemma": "は",
        "reading": "わ",
        "pos_coarse": "助詞",
        "pos_fine": "係助詞",
        "is_particle": true,
        "gloss_en": null
      },
      {
        "position": 2,
        "surface": "すぐ",
        "lemma": "すぐ",
        "reading": "すぐ",
        "pos_coarse": "副詞",
        "pos_fine": "*",
        "is_particle": false,
        "gloss_en": null
      },
      {
        "position": 3,
        "surface": "たっ",
        "lemma": "たつ",
        "reading": "たっ",
        "pos_coarse": "動詞",
        "pos_fine": "一般",
        "is_particle": false,
        "gloss_en": "to stand (up)"
      },
      {
        "position": 4,
        "surface": "て",
        "lemma": "て",
        "reading": "て",
        "pos_coarse": "助詞",
        "pos_fine": "接続助詞",
        "is_particle": true,
        "gloss_en": null
      },
      {
        "position": 5,
        "surface": "しまう",
        "lemma": "しまう",
        "reading": "しまう",
        "pos_coarse": "動詞",
        "pos_fine": "非自立可能",
        "is_particle": false,
        "gloss_en": "to finish"
      },
      {
        "position": 6,
        "surface": "。",
        "lemma": "。",
        "reading": "。",
        "pos_coarse": "補助記号",
        "pos_fine": "句点",
        "is_particle": false,
        "gloss_en": null
      }
    ],
    "particles": [
      {
        "position": 1,
        "particle": "は"
      },
      {
        "position": 4,
        "particle": "て"
      }
    ],
    "grammar_candidates": [
      {
        "key": "gari",
        "pattern": "がり",
        "label": "pessoa que tende a sentir algo (〜がり)"
      },
      {
        "key": "gp-118",
        "pattern": "しか～ない",
        "label": "só/apenas (〜しか〜ない)"
      },
      {
        "key": "gp-136",
        "pattern": "とかんがえられている",
        "label": "acredita-se que / pensa-se que (と考えられている)"
      },
      {
        "key": "gp-151",
        "pattern": "～てしまう",
        "label": "〜てしまう (concluir / fazer sem querer)"
      },
      {
        "key": "gp-70",
        "pattern": "ごとに",
        "label": "a cada / em cada (ごとに)"
      },
      {
        "key": "gp-91",
        "pattern": "の次に",
        "label": "〜の次に (no tsugi ni) — \"depois de / em seguida a\""
      },
      {
        "key": "kai",
        "pattern": "かい",
        "label": "partícula de pergunta informal (かい)"
      },
      {
        "key": "nakanaka-nai",
        "pattern": "なかなか～ない",
        "label": "custa a / não consegue de jeito nenhum (なかなか〜ない)"
      },
      {
        "key": "sasete-kudasai",
        "pattern": "させてください",
        "label": "させてください (deixe-me fazer / permita-me)"
      },
      {
        "key": "te-miru",
        "pattern": "てみる",
        "label": "〜てみる (tentar / experimentar fazer)"
      },
      {
        "key": "te-oku",
        "pattern": "～ておく",
        "label": "〜ておく (deixar feito de antemão / por precaução)"
      },
      {
        "key": "te-shimau-chau",
        "pattern": "てしまう / ちゃう",
        "label": "〜てしまう / 〜ちゃう (completar totalmente / arrependimento)"
      },
      {
        "key": "te-yokatta",
        "pattern": "～てよかった",
        "label": "que bom que... / ainda bem que (〜てよかった)"
      },
      {
        "key": "zenzen-nai",
        "pattern": "全然～ない（ぜんぜん～ない）",
        "label": "全然〜ない (zenzen~nai) — \"não... de jeito nenhum\""
      }
    ]
  },
  {
    "slug": "sent:tatoeba-196641",
    "jp": "ペンキがすぐはげてしまう。",
    "jp_source": "tatoeba:196641",
    "en": "This paint comes off easily.",
    "target": "てしまう",
    "topic": "top:n4-aspecto",
    "level": "n4",
    "tokens": [
      {
        "position": 0,
        "surface": "ペンキ",
        "lemma": "ペンキ",
        "reading": "ぺんき",
        "pos_coarse": "名詞",
        "pos_fine": "普通名詞",
        "is_particle": false,
        "gloss_en": null
      },
      {
        "position": 1,
        "surface": "が",
        "lemma": "が",
        "reading": "が",
        "pos_coarse": "助詞",
        "pos_fine": "格助詞",
        "is_particle": true,
        "gloss_en": null
      },
      {
        "position": 2,
        "surface": "すぐ",
        "lemma": "すぐ",
        "reading": "すぐ",
        "pos_coarse": "副詞",
        "pos_fine": "*",
        "is_particle": false,
        "gloss_en": null
      },
      {
        "position": 3,
        "surface": "はげ",
        "lemma": "はげる",
        "reading": "はげ",
        "pos_coarse": "動詞",
        "pos_fine": "一般",
        "is_particle": false,
        "gloss_en": null
      },
      {
        "position": 4,
        "surface": "て",
        "lemma": "て",
        "reading": "て",
        "pos_coarse": "助詞",
        "pos_fine": "接続助詞",
        "is_particle": true,
        "gloss_en": null
      },
      {
        "position": 5,
        "surface": "しまう",
        "lemma": "しまう",
        "reading": "しまう",
        "pos_coarse": "動詞",
        "pos_fine": "非自立可能",
        "is_particle": false,
        "gloss_en": "to finish"
      },
      {
        "position": 6,
        "surface": "。",
        "lemma": "。",
        "reading": "。",
        "pos_coarse": "補助記号",
        "pos_fine": "句点",
        "is_particle": false,
        "gloss_en": null
      }
    ],
    "particles": [
      {
        "position": 1,
        "particle": "が"
      },
      {
        "position": 4,
        "particle": "て"
      }
    ],
    "grammar_candidates": [
      {
        "key": "gari",
        "pattern": "がり",
        "label": "pessoa que tende a sentir algo (〜がり)"
      },
      {
        "key": "gp-118",
        "pattern": "しか～ない",
        "label": "só/apenas (〜しか〜ない)"
      },
      {
        "key": "gp-136",
        "pattern": "とかんがえられている",
        "label": "acredita-se que / pensa-se que (と考えられている)"
      },
      {
        "key": "gp-151",
        "pattern": "～てしまう",
        "label": "〜てしまう (concluir / fazer sem querer)"
      },
      {
        "key": "gp-70",
        "pattern": "ごとに",
        "label": "a cada / em cada (ごとに)"
      },
      {
        "key": "gp-91",
        "pattern": "の次に",
        "label": "〜の次に (no tsugi ni) — \"depois de / em seguida a\""
      },
      {
        "key": "kai",
        "pattern": "かい",
        "label": "partícula de pergunta informal (かい)"
      },
      {
        "key": "nakanaka-nai",
        "pattern": "なかなか～ない",
        "label": "custa a / não consegue de jeito nenhum (なかなか〜ない)"
      },
      {
        "key": "sasete-kudasai",
        "pattern": "させてください",
        "label": "させてください (deixe-me fazer / permita-me)"
      },
      {
        "key": "te-miru",
        "pattern": "てみる",
        "label": "〜てみる (tentar / experimentar fazer)"
      },
      {
        "key": "te-oku",
        "pattern": "～ておく",
        "label": "〜ておく (deixar feito de antemão / por precaução)"
      },
      {
        "key": "te-shimau-chau",
        "pattern": "てしまう / ちゃう",
        "label": "〜てしまう / 〜ちゃう (completar totalmente / arrependimento)"
      },
      {
        "key": "te-yokatta",
        "pattern": "～てよかった",
        "label": "que bom que... / ainda bem que (〜てよかった)"
      },
      {
        "key": "zenzen-nai",
        "pattern": "全然～ない（ぜんぜん～ない）",
        "label": "全然〜ない (zenzen~nai) — \"não... de jeito nenhum\""
      }
    ]
  },
  {
    "slug": "sent:tatoeba-234345",
    "jp": "あっ、バスが行ってしまう。",
    "jp_source": "tatoeba:234345",
    "en": "There goes our bus.",
    "target": "てしまう",
    "topic": "top:n4-aspecto",
    "level": "n4",
    "tokens": [
      {
        "position": 0,
        "surface": "あっ",
        "lemma": "あっ",
        "reading": "あっ",
        "pos_coarse": "感動詞",
        "pos_fine": "一般",
        "is_particle": false,
        "gloss_en": "ah"
      },
      {
        "position": 1,
        "surface": "、",
        "lemma": "、",
        "reading": "、",
        "pos_coarse": "補助記号",
        "pos_fine": "読点",
        "is_particle": false,
        "gloss_en": null
      },
      {
        "position": 2,
        "surface": "バス",
        "lemma": "バス",
        "reading": "ばす",
        "pos_coarse": "名詞",
        "pos_fine": "普通名詞",
        "is_particle": false,
        "gloss_en": "bus"
      },
      {
        "position": 3,
        "surface": "が",
        "lemma": "が",
        "reading": "が",
        "pos_coarse": "助詞",
        "pos_fine": "格助詞",
        "is_particle": true,
        "gloss_en": null
      },
      {
        "position": 4,
        "surface": "行っ",
        "lemma": "行く",
        "reading": "いっ",
        "pos_coarse": "動詞",
        "pos_fine": "非自立可能",
        "is_particle": false,
        "gloss_en": "to go"
      },
      {
        "position": 5,
        "surface": "て",
        "lemma": "て",
        "reading": "て",
        "pos_coarse": "助詞",
        "pos_fine": "接続助詞",
        "is_particle": true,
        "gloss_en": null
      },
      {
        "position": 6,
        "surface": "しまう",
        "lemma": "しまう",
        "reading": "しまう",
        "pos_coarse": "動詞",
        "pos_fine": "非自立可能",
        "is_particle": false,
        "gloss_en": "to finish"
      },
      {
        "position": 7,
        "surface": "。",
        "lemma": "。",
        "reading": "。",
        "pos_coarse": "補助記号",
        "pos_fine": "句点",
        "is_particle": false,
        "gloss_en": null
      }
    ],
    "particles": [
      {
        "position": 3,
        "particle": "が"
      },
      {
        "position": 5,
        "particle": "て"
      }
    ],
    "grammar_candidates": [
      {
        "key": "gari",
        "pattern": "がり",
        "label": "pessoa que tende a sentir algo (〜がり)"
      },
      {
        "key": "gp-118",
        "pattern": "しか～ない",
        "label": "só/apenas (〜しか〜ない)"
      },
      {
        "key": "gp-136",
        "pattern": "とかんがえられている",
        "label": "acredita-se que / pensa-se que (と考えられている)"
      },
      {
        "key": "gp-151",
        "pattern": "～てしまう",
        "label": "〜てしまう (concluir / fazer sem querer)"
      },
      {
        "key": "gp-70",
        "pattern": "ごとに",
        "label": "a cada / em cada (ごとに)"
      },
      {
        "key": "gp-91",
        "pattern": "の次に",
        "label": "〜の次に (no tsugi ni) — \"depois de / em seguida a\""
      },
      {
        "key": "kai",
        "pattern": "かい",
        "label": "partícula de pergunta informal (かい)"
      },
      {
        "key": "nakanaka-nai",
        "pattern": "なかなか～ない",
        "label": "custa a / não consegue de jeito nenhum (なかなか〜ない)"
      },
      {
        "key": "sasete-kudasai",
        "pattern": "させてください",
        "label": "させてください (deixe-me fazer / permita-me)"
      },
      {
        "key": "te-miru",
        "pattern": "てみる",
        "label": "〜てみる (tentar / experimentar fazer)"
      },
      {
        "key": "te-oku",
        "pattern": "～ておく",
        "label": "〜ておく (deixar feito de antemão / por precaução)"
      },
      {
        "key": "te-shimau-chau",
        "pattern": "てしまう / ちゃう",
        "label": "〜てしまう / 〜ちゃう (completar totalmente / arrependimento)"
      },
      {
        "key": "te-yokatta",
        "pattern": "～てよかった",
        "label": "que bom que... / ainda bem que (〜てよかった)"
      },
      {
        "key": "zenzen-nai",
        "pattern": "全然～ない（ぜんぜん～ない）",
        "label": "全然〜ない (zenzen~nai) — \"não... de jeito nenhum\""
      }
    ]
  },
  {
    "slug": "sent:tatoeba-10946950",
    "jp": "不安で夜中にふと目をさましてしまう。",
    "jp_source": "tatoeba:10946950",
    "en": "In the middle of the night, I'll suddenly wake up feeling worried.",
    "target": "てしまう",
    "topic": "top:n4-aspecto",
    "level": "n4",
    "tokens": [
      {
        "position": 0,
        "surface": "不安",
        "lemma": "不安",
        "reading": "ふあん",
        "pos_coarse": "名詞",
        "pos_fine": "普通名詞",
        "is_particle": false,
        "gloss_en": null
      },
      {
        "position": 1,
        "surface": "で",
        "lemma": "だ",
        "reading": "で",
        "pos_coarse": "助動詞",
        "pos_fine": "*",
        "is_particle": false,
        "gloss_en": null
      },
      {
        "position": 2,
        "surface": "夜中",
        "lemma": "夜中",
        "reading": "よなか",
        "pos_coarse": "名詞",
        "pos_fine": "普通名詞",
        "is_particle": false,
        "gloss_en": null
      },
      {
        "position": 3,
        "surface": "に",
        "lemma": "に",
        "reading": "に",
        "pos_coarse": "助詞",
        "pos_fine": "格助詞",
        "is_particle": true,
        "gloss_en": null
      },
      {
        "position": 4,
        "surface": "ふと",
        "lemma": "ふと",
        "reading": "ふと",
        "pos_coarse": "副詞",
        "pos_fine": "*",
        "is_particle": false,
        "gloss_en": null
      },
      {
        "position": 5,
        "surface": "目",
        "lemma": "目",
        "reading": "め",
        "pos_coarse": "名詞",
        "pos_fine": "普通名詞",
        "is_particle": false,
        "gloss_en": "eye"
      },
      {
        "position": 6,
        "surface": "を",
        "lemma": "を",
        "reading": "を",
        "pos_coarse": "助詞",
        "pos_fine": "格助詞",
        "is_particle": true,
        "gloss_en": null
      },
      {
        "position": 7,
        "surface": "さまし",
        "lemma": "さます",
        "reading": "さまし",
        "pos_coarse": "動詞",
        "pos_fine": "一般",
        "is_particle": false,
        "gloss_en": null
      },
      {
        "position": 8,
        "surface": "て",
        "lemma": "て",
        "reading": "て",
        "pos_coarse": "助詞",
        "pos_fine": "接続助詞",
        "is_particle": true,
        "gloss_en": null
      },
      {
        "position": 9,
        "surface": "しまう",
        "lemma": "しまう",
        "reading": "しまう",
        "pos_coarse": "動詞",
        "pos_fine": "非自立可能",
        "is_particle": false,
        "gloss_en": "to finish"
      },
      {
        "position": 10,
        "surface": "。",
        "lemma": "。",
        "reading": "。",
        "pos_coarse": "補助記号",
        "pos_fine": "句点",
        "is_particle": false,
        "gloss_en": null
      }
    ],
    "particles": [
      {
        "position": 3,
        "particle": "に"
      },
      {
        "position": 6,
        "particle": "を"
      },
      {
        "position": 8,
        "particle": "て"
      }
    ],
    "grammar_candidates": [
      {
        "key": "gari",
        "pattern": "がり",
        "label": "pessoa que tende a sentir algo (〜がり)"
      },
      {
        "key": "gp-118",
        "pattern": "しか～ない",
        "label": "só/apenas (〜しか〜ない)"
      },
      {
        "key": "gp-136",
        "pattern": "とかんがえられている",
        "label": "acredita-se que / pensa-se que (と考えられている)"
      },
      {
        "key": "gp-151",
        "pattern": "～てしまう",
        "label": "〜てしまう (concluir / fazer sem querer)"
      },
      {
        "key": "gp-70",
        "pattern": "ごとに",
        "label": "a cada / em cada (ごとに)"
      },
      {
        "key": "gp-91",
        "pattern": "の次に",
        "label": "〜の次に (no tsugi ni) — \"depois de / em seguida a\""
      },
      {
        "key": "kai",
        "pattern": "かい",
        "label": "partícula de pergunta informal (かい)"
      },
      {
        "key": "nakanaka-nai",
        "pattern": "なかなか～ない",
        "label": "custa a / não consegue de jeito nenhum (なかなか〜ない)"
      },
      {
        "key": "sasete-kudasai",
        "pattern": "させてください",
        "label": "させてください (deixe-me fazer / permita-me)"
      },
      {
        "key": "te-miru",
        "pattern": "てみる",
        "label": "〜てみる (tentar / experimentar fazer)"
      },
      {
        "key": "te-oku",
        "pattern": "～ておく",
        "label": "〜ておく (deixar feito de antemão / por precaução)"
      },
      {
        "key": "te-shimau-chau",
        "pattern": "てしまう / ちゃう",
        "label": "〜てしまう / 〜ちゃう (completar totalmente / arrependimento)"
      },
      {
        "key": "te-yokatta",
        "pattern": "～てよかった",
        "label": "que bom que... / ainda bem que (〜てよかった)"
      },
      {
        "key": "zenzen-nai",
        "pattern": "全然～ない（ぜんぜん～ない）",
        "label": "全然〜ない (zenzen~nai) — \"não... de jeito nenhum\""
      }
    ]
  }
]