[{"id": 277, "key": "koto-ni-suru", "pattern": "～ことにする", "level": "n4", "label_en": "koto ni suru", "also_known_as": ["ことにする", "koto ni suru"]}, {"id": 278, "key": "ku-suru", "pattern": "くする", "level": "n4", "label_en": "ku suru", "also_known_as": ["ku suru"]}, {"id": 279, "key": "kyuu-ni", "pattern": "急に（きゅうに）", "level": "n4", "label_en": "kyuu ni", "also_known_as": ["kyuu ni"]}, {"id": 280, "key": "made-ni", "pattern": "までに", "level": "n4", "label_en": "made ni", "also_known_as": ["made ni"]}, {"id": 281, "key": "mama", "pattern": "まま", "level": "n4", "label_en": "mama", "also_known_as": ["mama"]}, {"id": 282, "key": "matawa", "pattern": "または", "level": "n4", "label_en": "matawa", "also_known_as": ["matawa"]}]