[{"id": 229, "key": "gp-72", "pattern": "るところだ", "level": "n4", "label_en": "るところ", "also_known_as": []}, {"id": 230, "key": "gp-73", "pattern": "そういう", "level": "n4", "label_en": "そういう", "also_known_as": []}, {"id": 231, "key": "gp-74", "pattern": "ぜんぜん", "level": "n4", "label_en": "ぜんぜん", "also_known_as": []}, {"id": 232, "key": "gp-75", "pattern": "がる", "level": "n4", "label_en": "がる", "also_known_as": []}, {"id": 233, "key": "gp-76", "pattern": "みたいに・みたいな", "level": "n4", "label_en": "みたいにみたいな", "also_known_as": []}, {"id": 234, "key": "gp-77", "pattern": "のように・のような", "level": "n4", "label_en": "のようにのような", "also_known_as": []}]