[
  {
    "slug": "sent:gen-f5d8b6ff953f",
    "jp": "週末に働く人は少なくない",
    "jp_source": "ai-generated",
    "en": null,
    "target": "gp-104",
    "topic": "generated:grammar",
    "level": "n4",
    "ai_generated": 1,
    "tokens": [
      {
        "position": 0,
        "surface": "週末",
        "lemma": "週末",
        "reading": "しゅうまつ",
        "pos_coarse": "名詞",
        "pos_fine": "普通名詞",
        "is_particle": false,
        "gloss_en": null
      },
      {
        "position": 1,
        "surface": "に",
        "lemma": "に",
        "reading": "に",
        "pos_coarse": "助詞",
        "pos_fine": "格助詞",
        "is_particle": true,
        "gloss_en": null
      },
      {
        "position": 2,
        "surface": "働く",
        "lemma": "働く",
        "reading": "はたらく",
        "pos_coarse": "動詞",
        "pos_fine": "一般",
        "is_particle": false,
        "gloss_en": null
      },
      {
        "position": 3,
        "surface": "人",
        "lemma": "人",
        "reading": "ひと",
        "pos_coarse": "名詞",
        "pos_fine": "普通名詞",
        "is_particle": false,
        "gloss_en": null
      },
      {
        "position": 4,
        "surface": "は",
        "lemma": "は",
        "reading": "わ",
        "pos_coarse": "助詞",
        "pos_fine": "係助詞",
        "is_particle": true,
        "gloss_en": null
      },
      {
        "position": 5,
        "surface": "少なく",
        "lemma": "少ない",
        "reading": "すくなく",
        "pos_coarse": "形容詞",
        "pos_fine": "一般",
        "is_particle": false,
        "gloss_en": null
      },
      {
        "position": 6,
        "surface": "ない",
        "lemma": "ない",
        "reading": "ない",
        "pos_coarse": "形容詞",
        "pos_fine": "非自立可能",
        "is_particle": false,
        "gloss_en": null
      }
    ],
    "particles": [
      {
        "position": 1,
        "particle": "に"
      },
      {
        "position": 4,
        "particle": "は"
      }
    ],
    "grammar_candidates": [
      {
        "key": "gp-104",
        "pattern": "すくなくない",
        "label": "não são poucos / bastante (すくなくない)"
      }
    ]
  },
  {
    "slug": "sent:gen-18bcd3631e88",
    "jp": "毎日少し運動するようにしてほしい",
    "jp_source": "ai-generated",
    "en": null,
    "target": "gp-106",
    "topic": "generated:grammar",
    "level": "n4",
    "ai_generated": 1,
    "tokens": [
      {
        "position": 0,
        "surface": "毎日",
        "lemma": "毎日",
        "reading": "まいにち",
        "pos_coarse": "名詞",
        "pos_fine": "普通名詞",
        "is_particle": false,
        "gloss_en": null
      },
      {
        "position": 1,
        "surface": "少し",
        "lemma": "少し",
        "reading": "すこし",
        "pos_coarse": "副詞",
        "pos_fine": "*",
        "is_particle": false,
        "gloss_en": null
      },
      {
        "position": 2,
        "surface": "運動",
        "lemma": "運動",
        "reading": "うんどう",
        "pos_coarse": "名詞",
        "pos_fine": "普通名詞",
        "is_particle": false,
        "gloss_en": null
      },
      {
        "position": 3,
        "surface": "する",
        "lemma": "する",
        "reading": "する",
        "pos_coarse": "動詞",
        "pos_fine": "非自立可能",
        "is_particle": false,
        "gloss_en": null
      },
      {
        "position": 4,
        "surface": "よう",
        "lemma": "よう",
        "reading": "よう",
        "pos_coarse": "形状詞",
        "pos_fine": "助動詞語幹",
        "is_particle": false,
        "gloss_en": null
      },
      {
        "position": 5,
        "surface": "に",
        "lemma": "だ",
        "reading": "に",
        "pos_coarse": "助動詞",
        "pos_fine": "*",
        "is_particle": false,
        "gloss_en": null
      },
      {
        "position": 6,
        "surface": "し",
        "lemma": "する",
        "reading": "し",
        "pos_coarse": "動詞",
        "pos_fine": "非自立可能",
        "is_particle": false,
        "gloss_en": null
      },
      {
        "position": 7,
        "surface": "て",
        "lemma": "て",
        "reading": "て",
        "pos_coarse": "助詞",
        "pos_fine": "接続助詞",
        "is_particle": true,
        "gloss_en": null
      },
      {
        "position": 8,
        "surface": "ほしい",
        "lemma": "ほしい",
        "reading": "ほしい",
        "pos_coarse": "形容詞",
        "pos_fine": "非自立可能",
        "is_particle": false,
        "gloss_en": null
      }
    ],
    "particles": [
      {
        "position": 7,
        "particle": "て"
      }
    ],
    "grammar_candidates": [
      {
        "key": "gp-106",
        "pattern": "ように～てほしい",
        "label": "querer que (alguém) faça / passe a fazer (ように〜てほしい)"
      }
    ]
  },
  {
    "slug": "sent:gen-9c98c3debc99",
    "jp": "もっと早く来るようにしてほしい",
    "jp_source": "ai-generated",
    "en": null,
    "target": "gp-106",
    "topic": "generated:grammar",
    "level": "n4",
    "ai_generated": 1,
    "tokens": [
      {
        "position": 0,
        "surface": "もっと",
        "lemma": "もっと",
        "reading": "もっと",
        "pos_coarse": "副詞",
        "pos_fine": "*",
        "is_particle": false,
        "gloss_en": null
      },
      {
        "position": 1,
        "surface": "早く",
        "lemma": "早い",
        "reading": "はやく",
        "pos_coarse": "形容詞",
        "pos_fine": "一般",
        "is_particle": false,
        "gloss_en": null
      },
      {
        "position": 2,
        "surface": "来る",
        "lemma": "来る",
        "reading": "くる",
        "pos_coarse": "動詞",
        "pos_fine": "非自立可能",
        "is_particle": false,
        "gloss_en": null
      },
      {
        "position": 3,
        "surface": "よう",
        "lemma": "よう",
        "reading": "よう",
        "pos_coarse": "形状詞",
        "pos_fine": "助動詞語幹",
        "is_particle": false,
        "gloss_en": null
      },
      {
        "position": 4,
        "surface": "に",
        "lemma": "だ",
        "reading": "に",
        "pos_coarse": "助動詞",
        "pos_fine": "*",
        "is_particle": false,
        "gloss_en": null
      },
      {
        "position": 5,
        "surface": "し",
        "lemma": "する",
        "reading": "し",
        "pos_coarse": "動詞",
        "pos_fine": "非自立可能",
        "is_particle": false,
        "gloss_en": null
      },
      {
        "position": 6,
        "surface": "て",
        "lemma": "て",
        "reading": "て",
        "pos_coarse": "助詞",
        "pos_fine": "接続助詞",
        "is_particle": true,
        "gloss_en": null
      },
      {
        "position": 7,
        "surface": "ほしい",
        "lemma": "ほしい",
        "reading": "ほしい",
        "pos_coarse": "形容詞",
        "pos_fine": "非自立可能",
        "is_particle": false,
        "gloss_en": null
      }
    ],
    "particles": [
      {
        "position": 6,
        "particle": "て"
      }
    ],
    "grammar_candidates": [
      {
        "key": "gp-106",
        "pattern": "ように～てほしい",
        "label": "querer que (alguém) faça / passe a fazer (ように〜てほしい)"
      }
    ]
  },
  {
    "slug": "sent:gen-d0193ca6b4d8",
    "jp": "野菜を食べるようにしてほしい",
    "jp_source": "ai-generated",
    "en": null,
    "target": "gp-106",
    "topic": "generated:grammar",
    "level": "n4",
    "ai_generated": 1,
    "tokens": [
      {
        "position": 0,
        "surface": "野菜",
        "lemma": "野菜",
        "reading": "やさい",
        "pos_coarse": "名詞",
        "pos_fine": "普通名詞",
        "is_particle": false,
        "gloss_en": null
      },
      {
        "position": 1,
        "surface": "を",
        "lemma": "を",
        "reading": "を",
        "pos_coarse": "助詞",
        "pos_fine": "格助詞",
        "is_particle": true,
        "gloss_en": null
      },
      {
        "position": 2,
        "surface": "食べる",
        "lemma": "食べる",
        "reading": "たべる",
        "pos_coarse": "動詞",
        "pos_fine": "一般",
        "is_particle": false,
        "gloss_en": null
      },
      {
        "position": 3,
        "surface": "よう",
        "lemma": "よう",
        "reading": "よう",
        "pos_coarse": "形状詞",
        "pos_fine": "助動詞語幹",
        "is_particle": false,
        "gloss_en": null
      },
      {
        "position": 4,
        "surface": "に",
        "lemma": "だ",
        "reading": "に",
        "pos_coarse": "助動詞",
        "pos_fine": "*",
        "is_particle": false,
        "gloss_en": null
      },
      {
        "position": 5,
        "surface": "し",
        "lemma": "する",
        "reading": "し",
        "pos_coarse": "動詞",
        "pos_fine": "非自立可能",
        "is_particle": false,
        "gloss_en": null
      },
      {
        "position": 6,
        "surface": "て",
        "lemma": "て",
        "reading": "て",
        "pos_coarse": "助詞",
        "pos_fine": "接続助詞",
        "is_particle": true,
        "gloss_en": null
      },
      {
        "position": 7,
        "surface": "ほしい",
        "lemma": "ほしい",
        "reading": "ほしい",
        "pos_coarse": "形容詞",
        "pos_fine": "非自立可能",
        "is_particle": false,
        "gloss_en": null
      }
    ],
    "particles": [
      {
        "position": 1,
        "particle": "を"
      },
      {
        "position": 6,
        "particle": "て"
      }
    ],
    "grammar_candidates": [
      {
        "key": "gp-106",
        "pattern": "ように～てほしい",
        "label": "querer que (alguém) faça / passe a fazer (ように〜てほしい)"
      }
    ]
  },
  {
    "slug": "sent:gen-14de00536906",
    "jp": "子供にもっと本を読むようにしてほしい",
    "jp_source": "ai-generated",
    "en": null,
    "target": "gp-106",
    "topic": "generated:grammar",
    "level": "n4",
    "ai_generated": 1,
    "tokens": [
      {
        "position": 0,
        "surface": "子供",
        "lemma": "子供",
        "reading": "こども",
        "pos_coarse": "名詞",
        "pos_fine": "普通名詞",
        "is_particle": false,
        "gloss_en": null
      },
      {
        "position": 1,
        "surface": "に",
        "lemma": "に",
        "reading": "に",
        "pos_coarse": "助詞",
        "pos_fine": "格助詞",
        "is_particle": true,
        "gloss_en": null
      },
      {
        "position": 2,
        "surface": "もっと",
        "lemma": "もっと",
        "reading": "もっと",
        "pos_coarse": "副詞",
        "pos_fine": "*",
        "is_particle": false,
        "gloss_en": null
      },
      {
        "position": 3,
        "surface": "本",
        "lemma": "本",
        "reading": "ほん",
        "pos_coarse": "名詞",
        "pos_fine": "普通名詞",
        "is_particle": false,
        "gloss_en": null
      },
      {
        "position": 4,
        "surface": "を",
        "lemma": "を",
        "reading": "を",
        "pos_coarse": "助詞",
        "pos_fine": "格助詞",
        "is_particle": true,
        "gloss_en": null
      },
      {
        "position": 5,
        "surface": "読む",
        "lemma": "読む",
        "reading": "よむ",
        "pos_coarse": "動詞",
        "pos_fine": "一般",
        "is_particle": false,
        "gloss_en": null
      },
      {
        "position": 6,
        "surface": "よう",
        "lemma": "よう",
        "reading": "よう",
        "pos_coarse": "形状詞",
        "pos_fine": "助動詞語幹",
        "is_particle": false,
        "gloss_en": null
      },
      {
        "position": 7,
        "surface": "に",
        "lemma": "だ",
        "reading": "に",
        "pos_coarse": "助動詞",
        "pos_fine": "*",
        "is_particle": false,
        "gloss_en": null
      },
      {
        "position": 8,
        "surface": "し",
        "lemma": "する",
        "reading": "し",
        "pos_coarse": "動詞",
        "pos_fine": "非自立可能",
        "is_particle": false,
        "gloss_en": null
      },
      {
        "position": 9,
        "surface": "て",
        "lemma": "て",
        "reading": "て",
        "pos_coarse": "助詞",
        "pos_fine": "接続助詞",
        "is_particle": true,
        "gloss_en": null
      },
      {
        "position": 10,
        "surface": "ほしい",
        "lemma": "ほしい",
        "reading": "ほしい",
        "pos_coarse": "形容詞",
        "pos_fine": "非自立可能",
        "is_particle": false,
        "gloss_en": null
      }
    ],
    "particles": [
      {
        "position": 1,
        "particle": "に"
      },
      {
        "position": 4,
        "particle": "を"
      },
      {
        "position": 9,
        "particle": "て"
      }
    ],
    "grammar_candidates": [
      {
        "key": "gp-106",
        "pattern": "ように～てほしい",
        "label": "querer que (alguém) faça / passe a fazer (ように〜てほしい)"
      }
    ]
  }
]