[
  {
    "kind": "vocab",
    "vocab_id": 585,
    "word": "ポケット",
    "kana": "ポケット",
    "verb_class": null,
    "meaning": [
      "bolso"
    ],
    "need": 3
  },
  {
    "kind": "vocab",
    "vocab_id": 587,
    "word": "ポスト",
    "kana": "ポスト",
    "verb_class": null,
    "meaning": [
      "caixa de correio",
      "caixa postal"
    ],
    "need": 2
  },
  {
    "kind": "vocab",
    "vocab_id": 588,
    "word": "細い",
    "kana": "ほそい",
    "verb_class": null,
    "meaning": [
      "fino",
      "delgado",
      "esguio"
    ],
    "need": 3
  },
  {
    "kind": "vocab",
    "vocab_id": 592,
    "word": "本棚",
    "kana": "ほんだな",
    "verb_class": null,
    "meaning": [
      "estante de livros",
      "prateleira de livros"
    ],
    "need": 1
  },
  {
    "kind": "vocab",
    "vocab_id": 594,
    "word": "枚",
    "kana": "まい",
    "verb_class": null,
    "meaning": [
      "sufixo contador de objetos finos e planos (p. ex. folhas de papel, pratos, moedas)"
    ],
    "need": 3
  },
  {
    "kind": "vocab",
    "vocab_id": 596,
    "word": "毎月",
    "kana": "まいつき",
    "verb_class": null,
    "meaning": [
      "todo mês",
      "mensalmente"
    ],
    "need": 1
  },
  {
    "kind": "vocab",
    "vocab_id": 609,
    "word": "燐寸",
    "kana": "マッチ",
    "verb_class": null,
    "meaning": [
      "fósforo (para acender fogo)"
    ],
    "need": 3
  },
  {
    "kind": "vocab",
    "vocab_id": 611,
    "word": "丸い",
    "kana": "まるい",
    "verb_class": null,
    "meaning": [
      "redondo",
      "circular",
      "esférico"
    ],
    "need": 3
  },
  {
    "kind": "vocab",
    "vocab_id": 612,
    "word": "万",
    "kana": "まん",
    "verb_class": null,
    "meaning": [
      "10.000",
      "dez mil"
    ],
    "need": 2
  },
  {
    "kind": "vocab",
    "vocab_id": 613,
    "word": "万年筆",
    "kana": "まんねんひつ",
    "verb_class": null,
    "meaning": [
      "caneta-tinteiro"
    ],
    "need": 3
  },
  {
    "kind": "vocab",
    "vocab_id": 621,
    "word": "３日",
    "kana": "みっか",
    "verb_class": null,
    "meaning": [
      "dia 3 do mês"
    ],
    "need": 3
  },
  {
    "kind": "vocab",
    "vocab_id": 622,
    "word": "三つ",
    "kana": "みっつ",
    "verb_class": null,
    "meaning": [
      "três"
    ],
    "need": 3
  }
]